vk_botting/__init__.py
vk_botting/_types.py
vk_botting/abstract.py
vk_botting/attachments.py
vk_botting/bot.py
vk_botting/client.py
vk_botting/cog.py
vk_botting/commands.py
vk_botting/context.py
vk_botting/context_managers.py
vk_botting/conversions.py
vk_botting/cooldowns.py
vk_botting/exceptions.py
vk_botting/general.py
vk_botting/group.py
vk_botting/keyboard.py
vk_botting/limiters.py
vk_botting/message.py
vk_botting/states.py
vk_botting/user.py
vk_botting/utils.py
vk_botting/view.py
vk_botting-0.11.4.dist-info/LICENSE
vk_botting-0.11.4.dist-info/METADATA
vk_botting-0.11.4.dist-info/WHEEL
vk_botting-0.11.4.dist-info/top_level.txt
vk_botting-0.11.4.dist-info/RECORD
