Metadata-Version: 2.1
Name: vk-botting
Version: 0.11.4
Summary: A basic package for building async VK bots
Home-page: https://github.com/MrDandycorn/vk-botting
Author: MrDandycorn
License: MIT
Project-URL: Documentation, https://vk-botting.readthedocs.io/en/latest/
Project-URL: Issue tracker, https://github.com/MrDandycorn/vk-botting/issues
Platform: UNKNOWN
Classifier: Development Status :: 4 - Beta
Classifier: License :: OSI Approved :: MIT License
Classifier: Intended Audience :: Developers
Classifier: Natural Language :: English
Classifier: Natural Language :: Russian
Classifier: Operating System :: OS Independent
Classifier: Programming Language :: Python :: 3.6
Classifier: Programming Language :: Python :: 3.7
Classifier: Programming Language :: Python :: 3.8
Classifier: Programming Language :: Python :: 3.9
Classifier: Topic :: Internet
Classifier: Topic :: Software Development :: Libraries
Classifier: Topic :: Software Development :: Libraries :: Python Modules
Classifier: Topic :: Utilities
Requires-Python: >=3.6.0
Requires-Dist: aiohttp (<3.8.0,>=3.6.0)
Provides-Extra: docs
Requires-Dist: sphinx (==3.0.3) ; extra == 'docs'
Requires-Dist: sphinxcontrib-websupport ; extra == 'docs'
Requires-Dist: sphinxcontrib-trio (==1.1.2) ; extra == 'docs'
